{
  "source": "opensky-live",
  "time_unix": 1778837082,
  "time_iso": "2026-05-15T09:24:42.000Z",
  "bbox": {
    "lamin": 22,
    "lomin": 46,
    "lamax": 32,
    "lomax": 58
  },
  "okbk": {
    "lat": 29.2266,
    "lon": 47.9689
  },
  "counts": {
    "total": 18,
    "near_50nm": 0,
    "distant": 18
  },
  "aircraft": [
    {
      "icao24": "06a1d1",
      "callsign": "QQE532",
      "type": "",
      "state": "AIRBORNE_IN",
      "lat": 26.4817,
      "lon": 49.0328,
      "alt": 1075,
      "hdg": 88,
      "speed_kt": 514,
      "vrate_fpm": 65,
      "on_ground": false,
      "dist_nm": 174
    },
    {
      "icao24": "744828",
      "callsign": "RJA652",
      "type": "",
      "state": "CLEARED",
      "lat": 26.4917,
      "lon": 49.4211,
      "alt": 0,
      "hdg": 89,
      "speed_kt": 499,
      "vrate_fpm": 0,
      "on_ground": true,
      "dist_nm": 181
    },
    {
      "icao24": "06a2b2",
      "callsign": "QTR1171",
      "type": "",
      "state": "AIRBORNE_IN",
      "lat": 26.4922,
      "lon": 49.4911,
      "alt": 10225,
      "hdg": 89,
      "speed_kt": 523,
      "vrate_fpm": 0,
      "on_ground": false,
      "dist_nm": 183
    },
    {
      "icao24": "711540",
      "callsign": "KNE733",
      "type": "",
      "state": "AIRBORNE_OUT",
      "lat": 25.9385,
      "lon": 48.5061,
      "alt": 31700,
      "hdg": 241,
      "speed_kt": 423,
      "vrate_fpm": 1472,
      "on_ground": false,
      "dist_nm": 200
    },
    {
      "icao24": "3c1c82",
      "callsign": "VJH758",
      "type": "",
      "state": "AIRBORNE_IN",
      "lat": 26.2816,
      "lon": 50.518,
      "alt": 28175,
      "hdg": 98,
      "speed_kt": 506,
      "vrate_fpm": 0,
      "on_ground": false,
      "dist_nm": 222
    },
    {
      "icao24": "71005a",
      "callsign": "SVA3121",
      "type": "",
      "state": "AIRBORNE_IN",
      "lat": 24.1512,
      "lon": 52.3701,
      "alt": 36000,
      "hdg": 0,
      "speed_kt": 0,
      "vrate_fpm": 0,
      "on_ground": false,
      "dist_nm": 383
    },
    {
      "icao24": "010162",
      "callsign": "MSR902",
      "type": "",
      "state": "AIRBORNE_IN",
      "lat": 24.1512,
      "lon": 52.3701,
      "alt": 34000,
      "hdg": 0,
      "speed_kt": 0,
      "vrate_fpm": 0,
      "on_ground": false,
      "dist_nm": 383
    },
    {
      "icao24": "71147c",
      "callsign": "SVA568",
      "type": "",
      "state": "AIRBORNE_IN",
      "lat": 23.1791,
      "lon": 50.2427,
      "alt": 35000,
      "hdg": 99,
      "speed_kt": 528,
      "vrate_fpm": 0,
      "on_ground": false,
      "dist_nm": 383
    },
    {
      "icao24": "710108",
      "callsign": "SVA9784",
      "type": "",
      "state": "AIRBORNE_IN",
      "lat": 23.0484,
      "lon": 49.8645,
      "alt": 37000,
      "hdg": 103,
      "speed_kt": 540,
      "vrate_fpm": 0,
      "on_ground": false,
      "dist_nm": 384
    },
    {
      "icao24": "7105b0",
      "callsign": "SVA840",
      "type": "",
      "state": "AIRBORNE_OUT",
      "lat": 24.0865,
      "lon": 52.4283,
      "alt": 39000,
      "hdg": 119,
      "speed_kt": 10,
      "vrate_fpm": 1600,
      "on_ground": false,
      "dist_nm": 388
    },
    {
      "icao24": "750260",
      "callsign": "MAS8167",
      "type": "",
      "state": "AIRBORNE_IN",
      "lat": 22.8235,
      "lon": 50.8808,
      "alt": 39000,
      "hdg": 103,
      "speed_kt": 516,
      "vrate_fpm": 0,
      "on_ground": false,
      "dist_nm": 414
    },
    {
      "icao24": "8960fa",
      "callsign": "UAE806",
      "type": "",
      "state": "AIRBORNE_IN",
      "lat": 22.8235,
      "lon": 52.5085,
      "alt": 41000,
      "hdg": 94,
      "speed_kt": 537,
      "vrate_fpm": 0,
      "on_ground": false,
      "dist_nm": 453
    },
    {
      "icao24": "728676",
      "callsign": "IAW123",
      "type": "",
      "state": "AIRBORNE_IN",
      "lat": 24.1384,
      "lon": 55.8904,
      "alt": 13550,
      "hdg": 0,
      "speed_kt": 0,
      "vrate_fpm": -1663,
      "on_ground": false,
      "dist_nm": 516
    },
    {
      "icao24": "896434",
      "callsign": "ABY146",
      "type": "",
      "state": "AIRBORNE_IN",
      "lat": 24.1384,
      "lon": 55.8904,
      "alt": 22000,
      "hdg": 0,
      "speed_kt": 0,
      "vrate_fpm": 0,
      "on_ground": false,
      "dist_nm": 516
    },
    {
      "icao24": "507cac",
      "callsign": "FAD6138",
      "type": "",
      "state": "AIRBORNE_IN",
      "lat": 24.1384,
      "lon": 55.8904,
      "alt": 39000,
      "hdg": 0,
      "speed_kt": 0,
      "vrate_fpm": 0,
      "on_ground": false,
      "dist_nm": 516
    },
    {
      "icao24": "70612c",
      "callsign": "JZR121",
      "type": "",
      "state": "AIRBORNE_IN",
      "lat": 24.1385,
      "lon": 55.8904,
      "alt": 12000,
      "hdg": 0,
      "speed_kt": 0,
      "vrate_fpm": -1663,
      "on_ground": false,
      "dist_nm": 516
    },
    {
      "icao24": "896411",
      "callsign": "ABY442",
      "type": "",
      "state": "AIRBORNE_OUT",
      "lat": 24.1339,
      "lon": 56.0702,
      "alt": 28625,
      "hdg": 0,
      "speed_kt": 0,
      "vrate_fpm": 768,
      "on_ground": false,
      "dist_nm": 524
    },
    {
      "icao24": "8964da",
      "callsign": "ABY465",
      "type": "",
      "state": "AIRBORNE_OUT",
      "lat": 24.1339,
      "lon": 56.0703,
      "alt": 32775,
      "hdg": 0,
      "speed_kt": 0,
      "vrate_fpm": 1024,
      "on_ground": false,
      "dist_nm": 524
    }
  ]
}